scbl_db/__init__.py
scbl_db/bases.py
scbl_db/custom_types.py
scbl_db/models/data.py
scbl_db/models/entities.py
scbl_db/models/platforms/chromium.py
scbl_db/models/platforms/visium.py
scbl_db/models/platforms/xenium.py
scbl_db/models/processes.py
scbl_db/py.typed
scbl_db/utils.py
scbl_db-0.1.19.dist-info/LICENSE
scbl_db-0.1.19.dist-info/METADATA
scbl_db-0.1.19.dist-info/WHEEL
scbl_db-0.1.19.dist-info/RECORD
